{
  "name": "Cocktail",
  "base": "PersistedModel",
  "strict": false,
  "idInjection": false,
  "options": {
    "validateUpsert": true
  },
  "properties": {
    "date": {
      "type": "date"
    },
    "title": {
      "type": "string"
    },
    "lastUpdated": {
      "type": "date",
      "defaultFn": "now"
    },
    "preparation": {
      "type": "string"
    },
    "image": {
      "type": "string"
    },
    "ingredients": {
      "type": [
        "Ingredient"
      ]
    }
  },
  "validations": [],
  "relations": {},
  "acls": [
    {
      "accessType": "*",
      "principalType": "ROLE",
      "principalId": "$everyone",
      "permission": "DENY"
    },
    {
      "accessType": "EXECUTE",
      "principalType": "ROLE",
      "principalId": "$authenticated",
      "permission": "ALLOW",
      "property": "find"
    },
    {
      "accessType": "EXECUTE",
      "principalType": "ROLE",
      "principalId": "$authenticated",
      "permission": "ALLOW",
      "property": "create"
    },
    {
      "accessType": "EXECUTE",
      "principalType": "ROLE",
      "principalId": "$authenticated",
      "permission": "ALLOW",
      "property": "upsert"
    },
    {
      "accessType": "EXECUTE",
      "principalType": "ROLE",
      "principalId": "$authenticated",
      "permission": "ALLOW",
      "property": "deleteById"
    }
  ],
  "methods": {}
}
